<?xml version="1.0" encoding="utf-8"?><log event="ImportExportErr" loginGuid="9c7de57a-900f-4017-88f9-f22381dd6854" userId="2018248" userName="avusa\pklgn4bck" xmlns="http://www.teradp.com/schemas/GN4/1/Log.xsd"><description>XML import: object(s) input</description><error code="257" name="ImportError">Error importing XML: 'User avusa\pklgn4bck does not have permission to create story in folder '/Wires/AFP_Texts' (id: 1788) (ERR1330)' (ERR0257)</error><xml><story name="26bcd366-fa1e-4a2a-bcd6-ac2b5e7b9ad8" priority="high" xmlns:gn4="urn:schemas-teradp-com:gn4tera" xmlns:lc="http://www.teradp.com/schemas/GN4/1/LoginContext.xsd" xmlns:oc="http://www.teradp.com/schemas/GN4/1/OperationContext.xsd" xmlns:nav="http://www.teradp.com/schemas/GN4/1/ObjNav.xsd" xmlns:fn="http://www.teradp.com/schemas/GN4/1/Xslt" xmlns:edfn="http://www.teradp.com/schemas/GN4/1/EditorialXslt" xmlns=""><rights><ref><keyVal>AFP</keyVal></ref></rights><sourceRef><keyVal>AFP</keyVal></sourceRef><sourceId>urn:newsml:afp.com:20190925T070912Z:TX-PAR-EJF56:1</sourceId><followId>urn:newsml:afp.com:20190925T070912Z:TX-PAR-EJF56:1</followId><sourceFileName>afp.com-20190925T070912Z-TX-PAR-EJF56.xml</sourceFileName><keywords><item>RugbyU</item><item>WC</item><item>2019</item><item>FIJ</item><item>URU</item></keywords><folderRef><keyVal>/Wires/AFP_Texts</keyVal></folderRef><title>Minnows Uruguay stun Fiji 30-27 at Rugby World Cup</title><authors></authors><summary>South American minnows Uruguay stunned Fiji 30-27 on Wednesday for their first Rugby World Cup win since 2003 and the first upset of the tournament in Japan.Uruguay scored three tries to turn 24-12 ahead against a second-string Fiji outfit and then clung on in the second half to record the biggest victory in their history.th/ric</summary><city>Kamaishi</city><country>JPN</country><xmlText><p>South American minnows Uruguay stunned Fiji 30-27 on Wednesday for their first Rugby World Cup win since 2003 and the first upset of the tournament in Japan.</p><p>Uruguay scored three tries to turn 24-12 ahead against a second-string Fiji outfit and then clung on in the second half to record the biggest victory in their history.</p><p>th/ric</p><p class="credit">AFP</p></xmlText><xmlFormatRef><keyVal>XHTML</keyVal></xmlFormatRef></story></xml></log>