<?xml version="1.0" encoding="utf-8"?><log event="ImportExportErr" loginGuid="0cfbf252-5b2d-4e47-acc4-079c41f2429a" userId="4" userName="Administrator" xmlns="http://www.teradp.com/schemas/GN4/1/Log.xsd"><description>XML import: object(s) input</description><error code="257" name="ImportError">Error importing XML: 'There is no XML format with name: 'XHTML-BKC-TOP25-POLL' (ERR0206)' (ERR0257)</error><xml><story name="b9e90a51-82e8-4d52-95bb-f1f0ed456838" xmlns="urn:schemas-teradp-com:gn4tera" xmlns:msxsl="urn:schemas-microsoft-com:xslt"><authors>The Associated Press</authors><cats><ref weight="100" code="local" /></cats><folderRef><keyVal>/Wires/AP Stories</keyVal></folderRef><sourceRef><keyVal>AP (agate)</keyVal></sourceRef><title>BC-BKW--T25-AP Top 25</title><summary>The top 25 teams in The Associated Press' women's college basketball poll, with first-place votes in parentheses, records through Feb. 18, total points based on 25 points for a first-place vote through one point for a 25th-place vote and last...</summary><sourceId>57db730b-abf8-4c69-c698-7480dcb48025</sourceId><sourceRef><keyVal>AP</keyVal></sourceRef><instructions>Legacy:APLpoll%limit%r%BC-BKW--T25-AP Top 25;</instructions><objs /><xmlText><h2 style="display:none" xmlns="">The Top Twenty Five</h2><byline xmlns="">The Associated Press</byline><p /><p xmlns="">The top 25 teams in The Associated Press' women's college basketball poll, with first-place votes in parentheses, records through Feb. 18, total points based on 25 points for a first-place vote through one point for a 25th-place vote and last week's ranking:</p><table xmlns=""><tr><th></th><th>Record</th><th>Pts</th><th>Prv</th></tr><tr><td>1. UConn (32)</td><td>26-0</td><td>800</td><td>1</td></tr><tr><td>2. Mississippi St.</td><td>28-0</td><td>765</td><td>2</td></tr><tr><td>3. Baylor</td><td>25-1</td><td>735</td><td>3</td></tr><tr><td>4. Louisville</td><td>27-2</td><td>688</td><td>4</td></tr><tr><td>5. Notre Dame</td><td>25-2</td><td>686</td><td>5</td></tr><tr><td>6. Texas</td><td>22-4</td><td>632</td><td>6</td></tr><tr><td>7. South Carolina</td><td>22-5</td><td>597</td><td>8</td></tr><tr><td>8. Oregon</td><td>24-4</td><td>587</td><td>9</td></tr><tr><td>9. Florida St.</td><td>22-4</td><td>521</td><td>12</td></tr><tr><td>10. UCLA</td><td>21-5</td><td>501</td><td>7</td></tr><tr><td>11. Missouri</td><td>22-5</td><td>488</td><td>13</td></tr><tr><td>12. Oregon St.</td><td>21-6</td><td>443</td><td>15</td></tr><tr><td>13. Maryland</td><td>22-5</td><td>367</td><td>10</td></tr><tr><td>14. Ohio St.</td><td>22-6</td><td>359</td><td>16</td></tr><tr><td>15. Tennessee</td><td>21-6</td><td>358</td><td>11</td></tr><tr><td>16. Stanford</td><td>19-9</td><td>319</td><td>14</td></tr><tr><td>17. Texas A&amp;M</td><td>20-8</td><td>247</td><td>17</td></tr><tr><td>18. South Florida</td><td>22-5</td><td>229</td><td>22</td></tr><tr><td>19. Georgia</td><td>21-5</td><td>214</td><td>20</td></tr><tr><td>20. Duke</td><td>20-7</td><td>184</td><td>17</td></tr><tr><td>21. NC State</td><td>21-6</td><td>132</td><td>25</td></tr><tr><td>22. Green Bay</td><td>23-3</td><td>106</td><td>19</td></tr><tr><td>23. Belmont</td><td>26-3</td><td>98</td><td>24</td></tr><tr><td>24. LSU</td><td>18-7</td><td>87</td><td>-</td></tr><tr><td>25. Oklahoma St.</td><td>18-8</td><td>73</td><td>21</td></tr></table><p xmlns="">Others receiving votes: Minnesota 60, Dayton 29, Mercer 19, Miami 14, Arizona St. 12, Iowa 11, Michigan 10, West Virginia 7, Gonzaga 5, California 3, Cent Michigan 3, Oklahoma 3, Quinnipiac 3, Nebraska 3, Southern Cal 1, Syracuse 1.</p></xmlText><xmlFormatRef><keyVal xmlns="">XHTML-BKC-TOP25-POLL</keyVal></xmlFormatRef></story></xml></log>