<?xml version="1.0" encoding="utf-8"?><log event="ImportExportErr" loginGuid="0cfbf252-5b2d-4e47-acc4-079c41f2429a" userId="4" userName="Administrator" xmlns="http://www.teradp.com/schemas/GN4/1/Log.xsd"><description>XML import: object(s) input</description><error code="257" name="ImportError">Error importing XML: 'There is no XML format with name: 'XHTML-CAR-RESULTS' (ERR0206)' (ERR0257)</error><xml><story name="ef0687c0-7a1c-4d1f-88fc-ebd7252dade9" xmlns="urn:schemas-teradp-com:gn4tera" xmlns:msxsl="urn:schemas-microsoft-com:xslt"><cats><ref weight="100" code="local" /></cats><folderRef><keyVal>/Wires/AP Stories</keyVal></folderRef><sourceRef><keyVal>AP (agate)</keyVal></sourceRef><title>BC-CAR--NASCAR-Camping World Truck Results</title><summary>BC-CAR--NASCAR-Camping World Truck Results,0536</summary><sourceId>80b09e17-be85-4177-1779-7c34e7023b81</sourceId><sourceRef><keyVal>AP</keyVal></sourceRef><instructions>Legacy:z8065%-----%r%BC-CAR--NASCAR-Camping World Truck Results;</instructions><objs /><xmlText><h2 style="display:none" xmlns="">BC-CAR--NASCAR-Camping World Truck Results</h2><byline xmlns=""></byline><p /><hl2 xmlns="">BC-CAR--NASCAR-Camping World Truck Results,0536</hl2><hl2 xmlns="">NASCAR Camping World Truck-Stratosphere 200 Results</hl2><hl2 xmlns="">By The Associated Press</hl2><hl2 xmlns="">Saturday</hl2><hl2 xmlns="">At Las Vegas Motor Speedway</hl2><hl2 xmlns="">Las Vegas, Nev.</hl2><hl2 xmlns="">Lap length: 1.50 miles</hl2><hl2 xmlns="">(Start position in parentheses)</hl2><p xmlns="">1. (1) Kyle Busch, Toyota, 134 laps, 0 rating, 0 points.</p><p xmlns="">2. (3) Johnny Sauter, Chevrolet, 134, 0, 42.</p><p xmlns="">3. (6) Brett Moffitt, Toyota, 134, 0, 43.</p><p xmlns="">4. (8) Grant Enfinger, Ford, 134, 0, 35.</p><p xmlns="">5. (2) Stewart Friesen, Chevrolet, 134, 0, 49.</p><p xmlns="">6. (18) Dalton Sargeant, Chevrolet, 134, 0, 31.</p><p xmlns="">7. (15) Ben Rhodes, Ford, 134, 0, 42.</p><p xmlns="">8. (14) Cody Coughlin, Chevrolet, 134, 0, 31.</p><p xmlns="">9. (17) Justin Fontaine, Chevrolet, 134, 0, 28.</p><p xmlns="">10. (13) Austin Hill, Chevrolet, 134, 0, 27.</p><p xmlns="">11. (7) Justin Marks, Toyota, 134, 0, 26.</p><p xmlns="">12. (5) Noah Gragson, Toyota, 134, 0, 40.</p><p xmlns="">13. (4) Spencer Davis, Toyota, 134, 0, 34.</p><p xmlns="">14. (20) Wendell Chavous, Chevrolet, 134, 0, 23.</p><p xmlns="">15. (10) Myatt Snider, Ford, 133, 0, 37.</p><p xmlns="">16. (19) Austin Wayne Self, Toyota, 133, 0, 21.</p><p xmlns="">17. (16) Jordan Anderson, Chevrolet, 133, 0, 20.</p><p xmlns="">18. (24) Robby Lyons, Chevrolet, 133, 0, 19.</p><p xmlns="">19. (22) Michel Disdier, Chevrolet, 132, 0, 18.</p><p xmlns="">20. (23) Bayley Currey, Chevrolet, 132, 0, 17.</p><p xmlns="">21. (9) John Hunter Nemechek, Chevrolet, 130, 0, 0.</p><p xmlns="">22. (26) Mike Harmon, Chevrolet, 127, 0, 15.</p><p xmlns="">23. (31) BJ McLeod, Chevrolet, 123, 0, 0.</p><p xmlns="">24. (27) Jennifer Jo Cobb, Chevrolet, 123, 0, 13.</p><p xmlns="">25. (25) Josh Reaume, Chevrolet, engine, 119, 0, 12.</p><p xmlns="">26. (30) Norm Benning, Chevrolet, garage, 118, 0, 11.</p><p xmlns="">27. (28) Tommy Regan, Chevrolet, 112, 0, 10.</p><p xmlns="">28. (11) Justin Haley, Chevrolet, accident, 75, 0, 13.</p><p xmlns="">29. (12) Matt Crafton, Ford, brakes, 40, 0, 9.</p><p xmlns="">30. (32) Mike Senica, Chevrolet, electrical, 28, 0, 7.</p><p xmlns="">31. (21) Joe Nemechek, Chevrolet, vibration, 23, 0, 6.</p><p xmlns="">32. (29) Scott Stenzel, Chevrolet, electrical, 5, 0, 5.</p><p xmlns="">___</p><hl2 xmlns="">Race Statistics</hl2><p xmlns="">Average Speed of Race Winner: 122.658 mph.</p><p xmlns="">Time of Race: 1 hour, 38 minutes, 19 seconds.</p><p xmlns="">Margin of Victory: 0.437 seconds.</p><p xmlns="">Caution Flags: 5 for 25 laps.</p><p xmlns="">Lead Changes: 14 among 7 drivers.</p><p xmlns="">Lap Leaders: K.Busch 1-15; S.Friesen 16-20; N.Gragson 21-32; G.Enfinger 33-35; K.Busch 36-39; G.Enfinger 40; K.Busch 41-42; S.Friesen 43-68; B.Moffitt 69-70; K.Busch 71-83; B.Moffitt 84-108; K.Busch 109-114; D.Sargeant 115-117; J.Fontaine 118-119; K.Busch 120-134</p><p xmlns="">Leaders Summary (Driver, Times Led, Laps Led): K.Busch, 6 times for 49 laps; S.Friesen, 2 times for 29 laps; B.Moffitt, 2 times for 25 laps; N.Gragson, 1 time for 11 laps; G.Enfinger, 2 times for 2 laps; D.Sargeant, 1 time for 2 laps; J.Fontaine, 1 time for 1 lap.</p><p xmlns="">Wins: K.Busch, 1; B.Moffitt, 1; J.Sauter, 1.</p><p xmlns="">Top 10 in Points: 1. J.Sauter, 148; 2. B.Moffitt, 109; 3. G.Enfinger, 108; 4. N.Gragson, 107; 5. B.Rhodes, 103; 6. S.Friesen, 101; 7. S.Davis, 94; 8. D.Sargeant, 92; 9. M.Crafton, 84; 10. M.Snider, 84.</p><p xmlns="">___</p><hl2 xmlns="">NASCAR Driver Rating Formula</hl2><p xmlns="">A maximum of 150 points can be attained in a race.</p><p xmlns="">The formula combines the following categories: Wins, Finishes, Top-15 Finishes, Average Running Position While on Lead Lap, Average Speed Under Green, Fastest Lap, Led Most Laps, Lead-Lap Finish.</p></xmlText><xmlFormatRef><keyVal xmlns="">XHTML-CAR-RESULTS</keyVal></xmlFormatRef></story></xml></log>