<?xml version="1.0" encoding="utf-8"?><log event="ImportExportErr" loginGuid="0cfbf252-5b2d-4e47-acc4-079c41f2429a" userId="4" userName="Administrator" xmlns="http://www.teradp.com/schemas/GN4/1/Log.xsd"><description>XML import: object(s) input</description><error code="257" name="ImportError">Error importing XML: 'There is no XML format with name: 'XHTML-BKN-BOX' (ERR0206)' (ERR0257)</error><xml><story name="82d81768-3a7d-4738-93af-69761f08a3fe" xmlns="urn:schemas-teradp-com:gn4tera" xmlns:msxsl="urn:schemas-microsoft-com:xslt"><cats><ref weight="100" code="local" /></cats><folderRef><keyVal>/Wires/AP Stories</keyVal></folderRef><sourceRef><keyVal>AP (agate)</keyVal></sourceRef><title>BC-BKN--Bucks-Pacers Box</title><summary>BC-BKN--Bucks-Pacers Box</summary><sourceId>b6551859-474d-4920-920a-64f7fa2ec7e8</sourceId><sourceRef><keyVal>AP</keyVal></sourceRef><instructions>Legacy:z3057%-----%r%BC-BKN--Bucks-Pacers Box;</instructions><objs /><xmlText><h2 style="display:none" xmlns="">BC-BKN--Bucks-Pacers Box</h2><byline xmlns=""></byline><p /><hl2 xmlns="">BC-BKN--Bucks-Pacers Box</hl2><hl2 xmlns="">Bucks-Pacers, Box</hl2><table xmlns=""><tr><th>MILWAUKEE (89)</th></tr></table><p xmlns="">Middleton 1-7 4-5 6, Antetokounmpo 7-16 4-5 18, Henson 1-4 0-0 2, Bledsoe 10-22 4-4 26, Snell 3-5 0-0 9, Parker 7-10 0-0 15, Maker 0-4 0-0 0, Terry 4-5 0-0 9, Brown 1-2 2-2 4, Muhammad 0-1 0-0 0. Totals 34-76 14-16 89.&lt;</p><table xmlns=""><tr><th>INDIANA (92)</th></tr></table><p xmlns="">Bogdanovic 9-13 6-8 29, T.Young 4-8 0-0 10, Turner 1-3 3-4 5, Joseph 3-9 0-0 6, Oladipo 5-19 3-4 14, Robinson III 1-2 0-0 2, Leaf 0-0 0-0 0, Sabonis 5-9 1-1 11, J.Young 2-6 0-0 4, Stephenson 3-8 3-4 11. Totals 33-77 16-21 92.&lt;</p><table xmlns=""><tr><td>Milwaukee;17;29;23;20;—;89</td></tr><tr><td>Indiana;20;24;29;19;—;92</td></tr></table><p xmlns="">3-Point Goals_Milwaukee 7-23 (Snell 3-4, Bledsoe 2-10, Parker 1-2, Terry 1-2, Middleton 0-1, Maker 0-2, Antetokounmpo 0-2), Indiana 10-17 (Bogdanovic 5-7, T.Young 2-3, Stephenson 2-3, Oladipo 1-2, J.Young 0-1, Joseph 0-1). Fouled Out_None. Rebounds_Milwaukee 39 (Antetokounmpo 12), Indiana 37 (T.Young 7). Assists_Milwaukee 15 (Bledsoe 4), Indiana 18 (Oladipo 5). Total Fouls_Milwaukee 16, Indiana 15. Technicals_Milwaukee coach Bucks (Defensive three second). A_15,874 (18,500).</p></xmlText><xmlFormatRef><keyVal xmlns="">XHTML-BKN-BOX</keyVal></xmlFormatRef></story></xml></log>